{
    "elements": {
        "H": {
            "charge_specie": "-1",
            "gfw_formula": "H",
            "element_gfw": "1.008"
        },
        "H(1)": {
            "charge_specie": "-1",
            "gfw_formula": "0",
            "element_gfw": null
        },
        "E": {
            "charge_specie": "0",
            "gfw_formula": "0",
            "element_gfw": "0"
        },
        "O": {
            "charge_specie": "0",
            "gfw_formula": "O",
            "element_gfw": "15.999"
        },
        "O(-2)": {
            "charge_specie": "0",
            "gfw_formula": "0",
            "element_gfw": null
        },
        "Ca": {
            "charge_specie": "0",
            "gfw_formula": "Ca",
            "element_gfw": "40.08"
        },
        "Mg": {
            "charge_specie": "0",
            "gfw_formula": "Mg",
            "element_gfw": "24.31"
        },
        "Na": {
            "charge_specie": "0",
            "gfw_formula": "Na",
            "element_gfw": "22.99"
        },
        "K": {
            "charge_specie": "0",
            "gfw_formula": "K",
            "element_gfw": "39.1"
        },
        "Cl": {
            "charge_specie": "0",
            "gfw_formula": "Cl",
            "element_gfw": "35.45"
        },
        "S": {
            "charge_specie": "0",
            "gfw_formula": "SO4",
            "element_gfw": "32.064"
        },
        "S(6)": {
            "charge_specie": "0",
            "gfw_formula": "SO4",
            "element_gfw": null
        }
    },
    "minerals": {
        "Halite": {
            "formula": "NaCl",
            "mass": 58.44277
        },
        "Hydrohalite": {
            "formula": "NaCl:2H2O",
            "mass": 94.47333
        },
        "Sylvite": {
            "formula": "KCl",
            "mass": 74.5513
        },
        "Bischofite": {
            "formula": "MgCl2:6H2O",
            "mass": 203.30268
        },
        "Antarcticite": {
            "formula": "CaCl2:6H2O",
            "mass": 219.07568
        },
        "Tachyhydrite": {
            "formula": "CaCl2:(MgCl2)2:12H2O",
            "mass": 517.58936
        },
        "Carnallite": {
            "formula": "KCl:MgCl2:6H2O",
            "mass": 277.85398
        },
        "Thenardite": {
            "formula": "Na2SO4",
            "mass": 142.04214
        },
        "Mirabilite": {
            "formula": "Na2SO4:10H2O",
            "mass": 322.19494
        },
        "Arcanite": {
            "formula": "K2SO4",
            "mass": 174.2592
        },
        "Kieserite": {
            "formula": "MgSO4:H2O",
            "mass": 138.38288
        },
        "Starkeyite": {
            "formula": "MgSO4:4H2O",
            "mass": 192.42872
        },
        "Pentahydrite": {
            "formula": "MgSO4:5H2O",
            "mass": 210.44400000000002
        },
        "Hexahydrite": {
            "formula": "MgSO4:6H2O",
            "mass": 228.45927999999998
        },
        "Epsomite": {
            "formula": "MgSO4:7H2O",
            "mass": 246.47456
        },
        "Meridianiite": {
            "formula": "MgSO4:11H2O",
            "mass": 318.53568
        },
        "Anhydrite": {
            "formula": "CaSO4",
            "mass": 136.1406
        },
        "Bassanite": {
            "formula": "CaSO4:0.5H2O",
            "mass": 145.14824000000002
        },
        "Gypsum": {
            "formula": "CaSO4:2H2O",
            "mass": 172.17116000000001
        },
        "Glaserite": {
            "formula": "Na2SO4:3K2SO4",
            "mass": 664.81974
        },
        "Bloedite": {
            "formula": "Na2SO4:MgSO4:4H2O",
            "mass": 334.47086
        },
        "Glauberite": {
            "formula": "Na2SO4:CaSO4",
            "mass": 278.18273999999997
        },
        "Labile_Salt": {
            "formula": "Na4(SO4)2:CaSO4:2H2O",
            "mass": 456.25543999999996
        },
        "Leonite": {
            "formula": "K2SO4:MgSO4:4H2O",
            "mass": 366.68792
        },
        "Picromerite": {
            "formula": "K2SO4:MgSO4:6H2O",
            "mass": 402.71848
        },
        "Langbeinite": {
            "formula": "K2SO4:2MgSO4",
            "mass": 414.9944
        },
        "Syngenite": {
            "formula": "K2SO4:CaSO4:H2O",
            "mass": 328.41507999999993
        },
        "Kainite": {
            "formula": "KCl:MgSO4:2.75H2O",
            "mass": 244.46092000000002
        },
        "Polyhalite": {
            "formula": "K2SO4:MgSO4:Ca2(SO4)2:2H2O",
            "mass": 602.93856
        }
    }
}